Metadata-Version: 2.1
Name: odoo12-addon-shopinvader-quotation
Version: 12.0.2.1.0
Summary: Shopinvader Quotation
Home-page: https://github.com/shopinvader/odoo-shopinvader
Author: Akretion
License: AGPL-3
Platform: UNKNOWN
Classifier: Programming Language :: Python
Classifier: Framework :: Odoo
Classifier: License :: OSI Approved :: GNU Affero General Public License v3
Classifier: Development Status :: 5 - Production/Stable
Requires-Python: >=3.5
Requires-Dist: odoo12-addon-shopinvader
Requires-Dist: odoo (<12.1dev,>=12.0a)
